yaost/__init__.py
yaost/base.py
yaost/bbox.py
yaost/body.py
yaost/context.py
yaost/local_logging.py
yaost/module_watcher.py
yaost/packagefinder.py
yaost/path.py
yaost/project.py
yaost/transformation.py
yaost/util.py
yaost/variable.py
yaost/vector.py
yaost/ext/__init__.py
yaost/ext/construction.py
yaost/ext/ext.py
yaost/ext/extrusion.py
yaost/ext/hardware.py
yaost/ext/thread.py
yaost-2.2.2.dist-info/METADATA
yaost-2.2.2.dist-info/WHEEL
yaost-2.2.2.dist-info/licenses/LICENSE
yaost-2.2.2.dist-info/RECORD
