Metadata-Version: 2.4
Name: yaost
Version: 2.2.2
Summary: Yet another opensac translator
Project-URL: Repository, https://github.com/ariloulaleelay/yaost
Author-email: Andrey Proskurnev <andrey@proskurnev.ru>
License-Expression: MIT
License-File: LICENSE
Keywords: 3D CAD,OpenSCAD
Classifier: Development Status :: 4 - Beta
Classifier: License :: OSI Approved :: MIT License
Classifier: Programming Language :: Python :: 3
Requires-Python: >=3.10
Requires-Dist: lazy>=1.4
Requires-Dist: pyinotify-elephant-fork>=0.0.1
Provides-Extra: gears
Requires-Dist: shapely>=2.1; extra == 'gears'
